info/gianlucacosta/jardinero/__init__.py
info/gianlucacosta/jardinero/__main__.py
info/gianlucacosta/jardinero/app.py
info/gianlucacosta/jardinero/browser.py
info/gianlucacosta/jardinero/dictionary/__init__.py
info/gianlucacosta/jardinero/dictionary/sqlite/__init__.py
info/gianlucacosta/jardinero/dictionary/sqlite/strategy.py
info/gianlucacosta/jardinero/extensions.py
info/gianlucacosta/jardinero/static/964710d37d571f3d3c1a.svg
info/gianlucacosta/jardinero/static/@giancosta86/jardinero-frontend.8f0a82bd479cb959eaf0.js
info/gianlucacosta/jardinero/static/@giancosta86/jardinero-frontend.8f0a82bd479cb959eaf0.js.LICENSE.txt
info/gianlucacosta/jardinero/static/e79ecb444b1f41186fd3.svg
info/gianlucacosta/jardinero/static/favicon.svg
info/gianlucacosta/jardinero/static/index.html
info/gianlucacosta/jardinero/utils/__init__.py
info/gianlucacosta/jardinero/utils/downloads.py
info/gianlucacosta/jardinero/websockets/__init__.py
info/gianlucacosta/jardinero/websockets/dtos.py
info/gianlucacosta/jardinero/websockets/status.py
info.gianlucacosta.jardinero-1.1.3.dist-info/LICENSE
info.gianlucacosta.jardinero-1.1.3.dist-info/WHEEL
info.gianlucacosta.jardinero-1.1.3.dist-info/METADATA
info.gianlucacosta.jardinero-1.1.3.dist-info/RECORD
