Metadata-Version: 2.1
Name: info.gianlucacosta.jardinero
Version: 1.1.3
Summary: Extensible web application for exploring natural languages
Home-page: https://github.com/giancosta86/Jardinero
License: MIT
Keywords: dictionary,Wiktionary,wiki,pages,extract,terms,Python,TypeScript,React
Author: Gianluca Costa
Author-email: gianluca@gianlucacosta.info
Requires-Python: >=3.10,<4.0
Classifier: Development Status :: 5 - Production/Stable
Classifier: Environment :: Web Environment
Classifier: Intended Audience :: Developers
Classifier: License :: OSI Approved :: MIT License
Classifier: Operating System :: OS Independent
Classifier: Programming Language :: Python
Classifier: Programming Language :: Python :: 3
Classifier: Programming Language :: Python :: 3.10
Classifier: Topic :: Text Processing :: Linguistic
Requires-Dist: Flask (>=2.0.3,<3.0.0)
Requires-Dist: Flask-SocketIO (>=5.1.1,<6.0.0)
Requires-Dist: eventlet (>=0.33.0,<0.34.0)
Requires-Dist: info.gianlucacosta.wikiprism (>=1.0.0,<2.0.0)
Requires-Dist: requests (>=2.27.1,<3.0.0)
Project-URL: Documentation, https://github.com/giancosta86/Jardinero
Project-URL: Repository, https://github.com/giancosta86/Jardinero
